src/__init__.py
src/resolve_api.py
src/server.py
psm_davinci_resolve_mcp-1.0.1.dist-info/METADATA
psm_davinci_resolve_mcp-1.0.1.dist-info/WHEEL
psm_davinci_resolve_mcp-1.0.1.dist-info/entry_points.txt
psm_davinci_resolve_mcp-1.0.1.dist-info/licenses/LICENSE
psm_davinci_resolve_mcp-1.0.1.dist-info/RECORD
