Metadata-Version: 2.4
Name: psm-davinci-resolve-mcp
Version: 1.0.1
Summary: MCP server for DaVinci Resolve video editing - integrate AI with professional video editing
Project-URL: Homepage, https://github.com/PurpleSquirrelMedia/davinci-resolve-mcp
Project-URL: Repository, https://github.com/PurpleSquirrelMedia/davinci-resolve-mcp
Project-URL: Issues, https://github.com/PurpleSquirrelMedia/davinci-resolve-mcp/issues
Author-email: Matthew Karsten <matt@purplesquirrel.media>
License: MIT
License-File: LICENSE
Keywords: ai,anthropic,claude,davinci-resolve,mcp,video-editing
Classifier: Development Status :: 4 - Beta
Classifier: Intended Audience :: Developers
Classifier: License :: OSI Approved :: MIT License
Classifier: Operating System :: OS Independent
Classifier: Programming Language :: Python :: 3
Classifier: Programming Language :: Python :: 3.10
Classifier: Programming Language :: Python :: 3.11
Classifier: Programming Language :: Python :: 3.12
Classifier: Topic :: Multimedia :: Video
Classifier: Topic :: Software Development :: Libraries :: Python Modules
Requires-Python: >=3.10
Requires-Dist: mcp>=1.0.0
